LICENSE
MANIFEST.in
README.md
requirements.txt
setup.py
edi/__init__.py
edi/__main__.py
edi/bot.py
edi/config.py
edi/core.py
edi/db.py
edi/log.py
edi/slack.py
edi/units/__init__.py
edi/units/chatlog.py
edi/units/help.py
edi/units/quotes.py
edi/units/twitter.py
edi_slack.egg-info/PKG-INFO
edi_slack.egg-info/SOURCES.txt
edi_slack.egg-info/dependency_links.txt
edi_slack.egg-info/entry_points.txt
edi_slack.egg-info/requires.txt
edi_slack.egg-info/top_level.txt