Metadata-Version: 2.1
Name: edi-slack
Version: 0.5.0
Summary: Simple and elegant Slack bot
Home-page: https://github.com/jreese/edi
Author: John Reese
Author-email: john@noswap.com
License: MIT License
Platform: UNKNOWN
Classifier: License :: OSI Approved :: MIT License
Classifier: Operating System :: OS Independent
Classifier: Programming Language :: Python
Classifier: Programming Language :: Python :: 3
Classifier: Programming Language :: Python :: 3.6
Classifier: Topic :: Utilities
Classifier: Development Status :: 3 - Alpha
